tetris_game/__init__.py
tetris_game/constantes.py
tetris_game/core.py
tetris_game/assets/brique.png
tetris_game/assets/levelup.wav
tetris_game/assets/line.wav
tetris_game/assets/loose.wav
tetris_game/assets/mainSong.wav
tetris_game/assets/tetris.ico
tetris_game/assets/wall.wav
clo_tetris_game-0.0.6.dist-info/LICENCE
clo_tetris_game-0.0.6.dist-info/METADATA
clo_tetris_game-0.0.6.dist-info/WHEEL
clo_tetris_game-0.0.6.dist-info/entry_points.txt
clo_tetris_game-0.0.6.dist-info/top_level.txt
clo_tetris_game-0.0.6.dist-info/RECORD
